{
  "coverage": "48.34%",
  "expectCount": 1272,
  "actualCount": 615,
  "files": {
    "src/admin/AdminApplication.js": {
      "expectCount": 7,
      "actualCount": 1,
      "undocumentLines": [
        8,
        9,
        10,
        15,
        24,
        51
      ]
    },
    "src/admin/components/AdminHeader.js": {
      "expectCount": 2,
      "actualCount": 0,
      "undocumentLines": [
        4,
        5
      ]
    },
    "src/admin/components/AdminNav.js": {
      "expectCount": 9,
      "actualCount": 1,
      "undocumentLines": [
        8,
        9,
        11,
        14,
        21,
        26,
        31,
        95
      ]
    },
    "src/admin/components/AdminPage.js": {
      "expectCount": 16,
      "actualCount": 1,
      "undocumentLines": [
        1,
        11,
        12,
        14,
        15,
        18,
        27,
        31,
        40,
        49,
        144,
        151,
        156,
        168,
        172
      ]
    },
    "src/admin/components/AppearancePage.js": {
      "expectCount": 5,
      "actualCount": 0,
      "undocumentLines": [
        7,
        8,
        17,
        68,
        72
      ]
    },
    "src/admin/components/BasicsPage.js": {
      "expectCount": 8,
      "actualCount": 1,
      "undocumentLines": [
        4,
        5,
        7,
        14,
        19,
        28,
        37
      ]
    },
    "src/admin/components/DashboardPage.js": {
      "expectCount": 4,
      "actualCount": 0,
      "undocumentLines": [
        5,
        6,
        15,
        19
      ]
    },
    "src/admin/components/DashboardWidget.js": {
      "expectCount": 4,
      "actualCount": 2,
      "undocumentLines": [
        2,
        3
      ]
    },
    "src/admin/components/EditCustomCssModal.js": {
      "expectCount": 5,
      "actualCount": 0,
      "undocumentLines": [
        2,
        3,
        7,
        11,
        26
      ]
    },
    "src/admin/components/EditCustomFooterModal.js": {
      "expectCount": 5,
      "actualCount": 0,
      "undocumentLines": [
        2,
        3,
        7,
        11,
        21
      ]
    },
    "src/admin/components/EditCustomHeaderModal.js": {
      "expectCount": 5,
      "actualCount": 0,
      "undocumentLines": [
        2,
        3,
        7,
        11,
        21
      ]
    },
    "src/admin/components/EditGroupModal.js": {
      "expectCount": 16,
      "actualCount": 1,
      "undocumentLines": [
        14,
        16,
        17,
        18,
        19,
        20,
        21,
        24,
        28,
        35,
        43,
        99,
        109,
        111,
        120
      ]
    },
    "src/admin/components/ExtensionLinkButton.js": {
      "expectCount": 3,
      "actualCount": 0,
      "undocumentLines": [
        5,
        6,
        18
      ]
    },
    "src/admin/components/ExtensionPage.js": {
      "expectCount": 15,
      "actualCount": 0,
      "undocumentLines": [
        13,
        14,
        16,
        17,
        18,
        32,
        37,
        50,
        78,
        99,
        114,
        141,
        170,
        187,
        191
      ]
    },
    "src/admin/components/ExtensionPermissionGrid.js": {
      "expectCount": 9,
      "actualCount": 0,
      "undocumentLines": [
        4,
        5,
        7,
        10,
        19,
        23,
        27,
        31,
        35
      ]
    },
    "src/admin/components/ExtensionsWidget.js": {
      "expectCount": 7,
      "actualCount": 0,
      "undocumentLines": [
        6,
        7,
        9,
        12,
        16,
        23,
        33
      ]
    },
    "src/admin/components/HeaderPrimary.js": {
      "expectCount": 4,
      "actualCount": 2,
      "undocumentLines": [
        10,
        16
      ]
    },
    "src/admin/components/HeaderSecondary.js": {
      "expectCount": 3,
      "actualCount": 2,
      "undocumentLines": [
        11
      ]
    },
    "src/admin/components/LoadingModal.js": {
      "expectCount": 5,
      "actualCount": 1,
      "undocumentLines": [
        2,
        8,
        12,
        16
      ]
    },
    "src/admin/components/MailPage.js": {
      "expectCount": 12,
      "actualCount": 0,
      "undocumentLines": [
        6,
        7,
        9,
        13,
        22,
        23,
        24,
        32,
        40,
        91,
        100,
        110
      ]
    },
    "src/admin/components/PermissionDropdown.js": {
      "expectCount": 8,
      "actualCount": 0,
      "undocumentLines": [
        8,
        16,
        34,
        35,
        41,
        101,
        114,
        129
      ]
    },
    "src/admin/components/PermissionGrid.js": {
      "expectCount": 9,
      "actualCount": 0,
      "undocumentLines": [
        7,
        8,
        28,
        49,
        91,
        125,
        159,
        220,
        240
      ]
    },
    "src/admin/components/PermissionsPage.js": {
      "expectCount": 3,
      "actualCount": 0,
      "undocumentLines": [
        7,
        8,
        17
      ]
    },
    "src/admin/components/SessionDropdown.js": {
      "expectCount": 5,
      "actualCount": 2,
      "undocumentLines": [
        12,
        19,
        25
      ]
    },
    "src/admin/components/SettingDropdown.js": {
      "expectCount": 3,
      "actualCount": 0,
      "undocumentLines": [
        4,
        5,
        13
      ]
    },
    "src/admin/components/SettingsModal.js": {
      "expectCount": 12,
      "actualCount": 0,
      "undocumentLines": [
        5,
        6,
        8,
        9,
        12,
        16,
        26,
        35,
        40,
        52,
        56,
        62
      ]
    },
    "src/admin/components/StatusWidget.js": {
      "expectCount": 5,
      "actualCount": 0,
      "undocumentLines": [
        7,
        8,
        12,
        16,
        32
      ]
    },
    "src/admin/components/UploadImageButton.js": {
      "expectCount": 8,
      "actualCount": 4,
      "undocumentLines": [
        2,
        3,
        5,
        60
      ]
    },
    "src/admin/components/UserListPage.tsx": {
      "expectCount": 14,
      "actualCount": 10,
      "undocumentLines": [
        54,
        244,
        286,
        291
      ]
    },
    "src/admin/index.ts": {
      "expectCount": 1,
      "actualCount": 0,
      "undocumentLines": [
        7
      ]
    },
    "src/admin/resolvers/ExtensionPageResolver.ts": {
      "expectCount": 2,
      "actualCount": 2,
      "undocumentLines": []
    },
    "src/admin/routes.js": {
      "expectCount": 1,
      "actualCount": 1,
      "undocumentLines": []
    },
    "src/admin/utils/ExtensionData.js": {
      "expectCount": 13,
      "actualCount": 9,
      "undocumentLines": [
        2,
        3,
        4,
        5
      ]
    },
    "src/admin/utils/getCategorizedExtensions.js": {
      "expectCount": 1,
      "actualCount": 0,
      "undocumentLines": [
        1
      ]
    },
    "src/admin/utils/isExtensionEnabled.js": {
      "expectCount": 1,
      "actualCount": 0,
      "undocumentLines": [
        1
      ]
    },
    "src/admin/utils/saveSettings.js": {
      "expectCount": 1,
      "actualCount": 0,
      "undocumentLines": [
        1
      ]
    },
    "src/common/Application.js": {
      "expectCount": 31,
      "actualCount": 20,
      "undocumentLines": [
        146,
        154,
        155,
        156,
        157,
        159,
        164,
        176,
        192,
        204,
        276
      ]
    },
    "src/common/Component.ts": {
      "expectCount": 13,
      "actualCount": 11,
      "undocumentLines": [
        61,
        165
      ]
    },
    "src/common/Fragment.ts": {
      "expectCount": 4,
      "actualCount": 3,
      "undocumentLines": [
        55
      ]
    },
    "src/common/Model.js": {
      "expectCount": 19,
      "actualCount": 18,
      "undocumentLines": [
        216
      ]
    },
    "src/common/Session.js": {
      "expectCount": 6,
      "actualCount": 5,
      "undocumentLines": [
        6
      ]
    },
    "src/common/Store.js": {
      "expectCount": 12,
      "actualCount": 11,
      "undocumentLines": [
        6
      ]
    },
    "src/common/Translator.tsx": {
      "expectCount": 8,
      "actualCount": 4,
      "undocumentLines": [
        5,
        16,
        20,
        64
      ]
    },
    "src/common/components/Alert.tsx": {
      "expectCount": 2,
      "actualCount": 1,
      "undocumentLines": [
        11
      ]
    },
    "src/common/components/AlertManager.js": {
      "expectCount": 5,
      "actualCount": 1,
      "undocumentLines": [
        1,
        11,
        13,
        16
      ]
    },
    "src/common/components/Badge.js": {
      "expectCount": 2,
      "actualCount": 1,
      "undocumentLines": [
        20
      ]
    },
    "src/common/components/Button.js": {
      "expectCount": 3,
      "actualCount": 2,
      "undocumentLines": [
        27
      ]
    },
    "src/common/components/Checkbox.js": {
      "expectCount": 4,
      "actualCount": 3,
      "undocumentLines": [
        20
      ]
    },
    "src/common/components/ConfirmDocumentUnload.js": {
      "expectCount": 6,
      "actualCount": 1,
      "undocumentLines": [
        20,
        24,
        26,
        30,
        35
      ]
    },
    "src/common/components/Dropdown.js": {
      "expectCount": 9,
      "actualCount": 3,
      "undocumentLines": [
        23,
        32,
        34,
        37,
        44,
        113
      ]
    },
    "src/common/components/EditUserModal.js": {
      "expectCount": 18,
      "actualCount": 2,
      "undocumentLines": [
        13,
        16,
        17,
        18,
        19,
        20,
        21,
        25,
        29,
        33,
        42,
        117,
        118,
        135,
        159,
        170
      ]
    },
    "src/common/components/FieldSet.js": {
      "expectCount": 2,
      "actualCount": 1,
      "undocumentLines": [
        14
      ]
    },
    "src/common/components/GroupBadge.js": {
      "expectCount": 2,
      "actualCount": 0,
      "undocumentLines": [
        2,
        3
      ]
    },
    "src/common/components/Link.js": {
      "expectCount": 2,
      "actualCount": 1,
      "undocumentLines": [
        13
      ]
    },
    "src/common/components/LinkButton.js": {
      "expectCount": 4,
      "actualCount": 2,
      "undocumentLines": [
        18,
        24
      ]
    },
    "src/common/components/LoadingIndicator.tsx": {
      "expectCount": 3,
      "actualCount": 1,
      "undocumentLines": [
        1,
        34
      ]
    },
    "src/common/components/Modal.js": {
      "expectCount": 15,
      "actualCount": 11,
      "undocumentLines": [
        24,
        29,
        43,
        125
      ]
    },
    "src/common/components/ModalManager.js": {
      "expectCount": 5,
      "actualCount": 1,
      "undocumentLines": [
        9,
        20,
        28,
        44
      ]
    },
    "src/common/components/Navigation.js": {
      "expectCount": 5,
      "actualCount": 4,
      "undocumentLines": [
        21
      ]
    },
    "src/common/components/Page.js": {
      "expectCount": 7,
      "actualCount": 4,
      "undocumentLines": [
        10,
        41,
        57
      ]
    },
    "src/common/components/Placeholder.js": {
      "expectCount": 2,
      "actualCount": 1,
      "undocumentLines": [
        12
      ]
    },
    "src/common/components/RequestErrorModal.js": {
      "expectCount": 4,
      "actualCount": 0,
      "undocumentLines": [
        2,
        3,
        7,
        11
      ]
    },
    "src/common/components/Select.js": {
      "expectCount": 3,
      "actualCount": 1,
      "undocumentLines": [
        1,
        21
      ]
    },
    "src/common/components/SelectDropdown.js": {
      "expectCount": 4,
      "actualCount": 2,
      "undocumentLines": [
        36,
        42
      ]
    },
    "src/common/components/Separator.js": {
      "expectCount": 2,
      "actualCount": 1,
      "undocumentLines": [
        7
      ]
    },
    "src/common/components/SplitDropdown.js": {
      "expectCount": 4,
      "actualCount": 2,
      "undocumentLines": [
        10,
        16
      ]
    },
    "src/common/components/Switch.js": {
      "expectCount": 3,
      "actualCount": 1,
      "undocumentLines": [
        8,
        13
      ]
    },
    "src/common/components/TextEditor.js": {
      "expectCount": 13,
      "actualCount": 7,
      "undocumentLines": [
        22,
        38,
        50,
        55,
        65,
        80
      ]
    },
    "src/common/components/TextEditorButton.js": {
      "expectCount": 3,
      "actualCount": 1,
      "undocumentLines": [
        9,
        19
      ]
    },
    "src/common/components/Tooltip.tsx": {
      "expectCount": 15,
      "actualCount": 2,
      "undocumentLines": [
        41,
        42,
        43,
        44,
        45,
        47,
        77,
        106,
        112,
        118,
        132,
        144,
        170
      ]
    },
    "src/common/extend/Model.js": {
      "expectCount": 11,
      "actualCount": 0,
      "undocumentLines": [
        1,
        2,
        3,
        4,
        5,
        7,
        9,
        12,
        17,
        22,
        27
      ]
    },
    "src/common/extend/PostTypes.js": {
      "expectCount": 4,
      "actualCount": 0,
      "undocumentLines": [
        1,
        2,
        4,
        9
      ]
    },
    "src/common/extend/Routes.js": {
      "expectCount": 4,
      "actualCount": 0,
      "undocumentLines": [
        1,
        2,
        4,
        12
      ]
    },
    "src/common/extend.js": {
      "expectCount": 2,
      "actualCount": 2,
      "undocumentLines": []
    },
    "src/common/helpers/avatar.tsx": {
      "expectCount": 2,
      "actualCount": 1,
      "undocumentLines": [
        1
      ]
    },
    "src/common/helpers/fullTime.tsx": {
      "expectCount": 1,
      "actualCount": 1,
      "undocumentLines": []
    },
    "src/common/helpers/highlight.tsx": {
      "expectCount": 1,
      "actualCount": 1,
      "undocumentLines": []
    },
    "src/common/helpers/humanTime.tsx": {
      "expectCount": 1,
      "actualCount": 1,
      "undocumentLines": []
    },
    "src/common/helpers/icon.tsx": {
      "expectCount": 2,
      "actualCount": 1,
      "undocumentLines": [
        1
      ]
    },
    "src/common/helpers/listItems.tsx": {
      "expectCount": 3,
      "actualCount": 1,
      "undocumentLines": [
        4,
        8
      ]
    },
    "src/common/helpers/punctuateSeries.js": {
      "expectCount": 1,
      "actualCount": 1,
      "undocumentLines": []
    },
    "src/common/helpers/userOnline.tsx": {
      "expectCount": 1,
      "actualCount": 1,
      "undocumentLines": []
    },
    "src/common/helpers/username.tsx": {
      "expectCount": 1,
      "actualCount": 1,
      "undocumentLines": []
    },
    "src/common/index.js": {
      "expectCount": 2,
      "actualCount": 0,
      "undocumentLines": [
        20,
        22
      ]
    },
    "src/common/models/Discussion.js": {
      "expectCount": 1,
      "actualCount": 0,
      "undocumentLines": [
        5
      ]
    },
    "src/common/models/Forum.js": {
      "expectCount": 2,
      "actualCount": 0,
      "undocumentLines": [
        2,
        3
      ]
    },
    "src/common/models/Group.js": {
      "expectCount": 1,
      "actualCount": 0,
      "undocumentLines": [
        3
      ]
    },
    "src/common/models/Notification.js": {
      "expectCount": 1,
      "actualCount": 0,
      "undocumentLines": [
        2
      ]
    },
    "src/common/models/Post.js": {
      "expectCount": 1,
      "actualCount": 0,
      "undocumentLines": [
        4
      ]
    },
    "src/common/models/User.js": {
      "expectCount": 1,
      "actualCount": 0,
      "undocumentLines": [
        7
      ]
    },
    "src/common/resolvers/DefaultResolver.ts": {
      "expectCount": 8,
      "actualCount": 5,
      "undocumentLines": [
        11,
        12,
        13
      ]
    },
    "src/common/states/AlertManagerState.ts": {
      "expectCount": 8,
      "actualCount": 7,
      "undocumentLines": [
        9
      ]
    },
    "src/common/states/ModalManagerState.js": {
      "expectCount": 6,
      "actualCount": 2,
      "undocumentLines": [
        2,
        3,
        4,
        42
      ]
    },
    "src/common/states/PageState.js": {
      "expectCount": 7,
      "actualCount": 1,
      "undocumentLines": [
        2,
        3,
        4,
        5,
        25,
        29
      ]
    },
    "src/common/utils/BasicEditorDriver.ts": {
      "expectCount": 17,
      "actualCount": 15,
      "undocumentLines": [
        11,
        12
      ]
    },
    "src/common/utils/Drawer.js": {
      "expectCount": 6,
      "actualCount": 4,
      "undocumentLines": [
        7,
        60
      ]
    },
    "src/common/utils/ItemList.ts": {
      "expectCount": 15,
      "actualCount": 11,
      "undocumentLines": [
        8,
        9,
        10,
        21
      ]
    },
    "src/common/utils/RequestError.ts": {
      "expectCount": 8,
      "actualCount": 1,
      "undocumentLines": [
        8,
        9,
        10,
        11,
        12,
        14,
        19
      ]
    },
    "src/common/utils/ScrollListener.js": {
      "expectCount": 10,
      "actualCount": 6,
      "undocumentLines": [
        1,
        15,
        16,
        71
      ]
    },
    "src/common/utils/SubtreeRetainer.js": {
      "expectCount": 7,
      "actualCount": 5,
      "undocumentLines": [
        29,
        30
      ]
    },
    "src/common/utils/abbreviateNumber.ts": {
      "expectCount": 1,
      "actualCount": 1,
      "undocumentLines": []
    },
    "src/common/utils/anchorScroll.js": {
      "expectCount": 1,
      "actualCount": 1,
      "undocumentLines": []
    },
    "src/common/utils/bidi.js": {
      "expectCount": 2,
      "actualCount": 0,
      "undocumentLines": [
        42,
        1
      ]
    },
    "src/common/utils/classList.ts": {
      "expectCount": 1,
      "actualCount": 1,
      "undocumentLines": []
    },
    "src/common/utils/computed.js": {
      "expectCount": 1,
      "actualCount": 1,
      "undocumentLines": []
    },
    "src/common/utils/escapeRegExp.ts": {
      "expectCount": 2,
      "actualCount": 1,
      "undocumentLines": [
        1
      ]
    },
    "src/common/utils/extract.ts": {
      "expectCount": 1,
      "actualCount": 1,
      "undocumentLines": []
    },
    "src/common/utils/extractText.js": {
      "expectCount": 1,
      "actualCount": 1,
      "undocumentLines": []
    },
    "src/common/utils/formatNumber.ts": {
      "expectCount": 1,
      "actualCount": 1,
      "undocumentLines": []
    },
    "src/common/utils/humanTime.ts": {
      "expectCount": 1,
      "actualCount": 1,
      "undocumentLines": []
    },
    "src/common/utils/insertText.ts": {
      "expectCount": 2,
      "actualCount": 1,
      "undocumentLines": [
        5
      ]
    },
    "src/common/utils/liveHumanTimes.ts": {
      "expectCount": 2,
      "actualCount": 2,
      "undocumentLines": []
    },
    "src/common/utils/mapRoutes.js": {
      "expectCount": 1,
      "actualCount": 1,
      "undocumentLines": []
    },
    "src/common/utils/mixin.js": {
      "expectCount": 1,
      "actualCount": 1,
      "undocumentLines": []
    },
    "src/common/utils/patchMithril.js": {
      "expectCount": 1,
      "actualCount": 0,
      "undocumentLines": [
        2
      ]
    },
    "src/common/utils/proxifyCompat.ts": {
      "expectCount": 1,
      "actualCount": 0,
      "undocumentLines": [
        1
      ]
    },
    "src/common/utils/setRouteWithForcedRefresh.ts": {
      "expectCount": 1,
      "actualCount": 1,
      "undocumentLines": []
    },
    "src/common/utils/string.ts": {
      "expectCount": 4,
      "actualCount": 4,
      "undocumentLines": []
    },
    "src/common/utils/stringToColor.ts": {
      "expectCount": 2,
      "actualCount": 2,
      "undocumentLines": []
    },
    "src/common/utils/styleSelectedText.ts": {
      "expectCount": 12,
      "actualCount": 11,
      "undocumentLines": [
        6
      ]
    },
    "src/common/utils/subclassOf.js": {
      "expectCount": 1,
      "actualCount": 1,
      "undocumentLines": []
    },
    "src/common/utils/withAttr.ts": {
      "expectCount": 1,
      "actualCount": 1,
      "undocumentLines": []
    },
    "src/forum/ForumApplication.js": {
      "expectCount": 14,
      "actualCount": 10,
      "undocumentLines": [
        20,
        75,
        80,
        82
      ]
    },
    "src/forum/components/AffixedSidebar.js": {
      "expectCount": 6,
      "actualCount": 1,
      "undocumentLines": [
        15,
        19,
        22,
        26,
        31
      ]
    },
    "src/forum/components/AvatarEditor.js": {
      "expectCount": 15,
      "actualCount": 13,
      "undocumentLines": [
        20,
        38
      ]
    },
    "src/forum/components/ChangeEmailModal.js": {
      "expectCount": 12,
      "actualCount": 4,
      "undocumentLines": [
        10,
        35,
        39,
        43,
        92,
        101,
        102,
        115
      ]
    },
    "src/forum/components/ChangePasswordModal.js": {
      "expectCount": 6,
      "actualCount": 1,
      "undocumentLines": [
        9,
        13,
        17,
        33,
        35
      ]
    },
    "src/forum/components/CommentPost.js": {
      "expectCount": 13,
      "actualCount": 5,
      "undocumentLines": [
        22,
        43,
        54,
        68,
        71,
        76,
        81,
        87
      ]
    },
    "src/forum/components/Composer.js": {
      "expectCount": 29,
      "actualCount": 20,
      "undocumentLines": [
        14,
        31,
        34,
        61,
        74,
        86,
        91,
        141,
        249
      ]
    },
    "src/forum/components/ComposerBody.js": {
      "expectCount": 9,
      "actualCount": 6,
      "undocumentLines": [
        28,
        30,
        48
      ]
    },
    "src/forum/components/ComposerButton.js": {
      "expectCount": 2,
      "actualCount": 1,
      "undocumentLines": [
        8
      ]
    },
    "src/forum/components/ComposerPostPreview.js": {
      "expectCount": 6,
      "actualCount": 1,
      "undocumentLines": [
        17,
        23,
        29,
        46,
        49
      ]
    },
    "src/forum/components/DiscussionComposer.js": {
      "expectCount": 10,
      "actualCount": 4,
      "undocumentLines": [
        17,
        26,
        38,
        68,
        85,
        86
      ]
    },
    "src/forum/components/DiscussionHero.js": {
      "expectCount": 3,
      "actualCount": 2,
      "undocumentLines": [
        13
      ]
    },
    "src/forum/components/DiscussionList.js": {
      "expectCount": 2,
      "actualCount": 1,
      "undocumentLines": [
        16
      ]
    },
    "src/forum/components/DiscussionListItem.js": {
      "expectCount": 13,
      "actualCount": 7,
      "undocumentLines": [
        31,
        46,
        52,
        70,
        114,
        125
      ]
    },
    "src/forum/components/DiscussionListPane.js": {
      "expectCount": 6,
      "actualCount": 2,
      "undocumentLines": [
        5,
        20,
        32,
        65
      ]
    },
    "src/forum/components/DiscussionPage.js": {
      "expectCount": 14,
      "actualCount": 8,
      "undocumentLines": [
        18,
        20,
        47,
        50,
        65,
        152
      ]
    },
    "src/forum/components/DiscussionRenamedNotification.js": {
      "expectCount": 4,
      "actualCount": 1,
      "undocumentLines": [
        12,
        16,
        21
      ]
    },
    "src/forum/components/DiscussionRenamedPost.js": {
      "expectCount": 4,
      "actualCount": 1,
      "undocumentLines": [
        13,
        17,
        25
      ]
    },
    "src/forum/components/DiscussionsSearchSource.tsx": {
      "expectCount": 4,
      "actualCount": 1,
      "undocumentLines": [
        10,
        12,
        27
      ]
    },
    "src/forum/components/DiscussionsUserPage.js": {
      "expectCount": 5,
      "actualCount": 1,
      "undocumentLines": [
        10,
        15,
        17,
        24
      ]
    },
    "src/forum/components/EditPostComposer.js": {
      "expectCount": 8,
      "actualCount": 3,
      "undocumentLines": [
        6,
        25,
        34,
        68,
        70
      ]
    },
    "src/forum/components/EventPost.js": {
      "expectCount": 7,
      "actualCount": 5,
      "undocumentLines": [
        19,
        25
      ]
    },
    "src/forum/components/ForgotPasswordModal.js": {
      "expectCount": 11,
      "actualCount": 3,
      "undocumentLines": [
        15,
        33,
        37,
        41,
        81,
        83,
        93,
        97
      ]
    },
    "src/forum/components/HeaderPrimary.js": {
      "expectCount": 3,
      "actualCount": 2,
      "undocumentLines": [
        10
      ]
    },
    "src/forum/components/HeaderSecondary.js": {
      "expectCount": 3,
      "actualCount": 2,
      "undocumentLines": [
        18
      ]
    },
    "src/forum/components/IndexPage.js": {
      "expectCount": 18,
      "actualCount": 8,
      "undocumentLines": [
        20,
        22,
        28,
        41,
        42,
        45,
        67,
        72,
        111,
        118
      ]
    },
    "src/forum/components/LoadingPost.js": {
      "expectCount": 2,
      "actualCount": 1,
      "undocumentLines": [
        9
      ]
    },
    "src/forum/components/LogInButton.js": {
      "expectCount": 2,
      "actualCount": 1,
      "undocumentLines": [
        12
      ]
    },
    "src/forum/components/LogInButtons.js": {
      "expectCount": 3,
      "actualCount": 2,
      "undocumentLines": [
        8
      ]
    },
    "src/forum/components/LogInModal.js": {
      "expectCount": 17,
      "actualCount": 6,
      "undocumentLines": [
        19,
        44,
        48,
        52,
        60,
        66,
        107,
        152,
        156,
        158,
        171
      ]
    },
    "src/forum/components/Notification.js": {
      "expectCount": 7,
      "actualCount": 6,
      "undocumentLines": [
        20
      ]
    },
    "src/forum/components/NotificationGrid.js": {
      "expectCount": 13,
      "actualCount": 10,
      "undocumentLines": [
        15,
        40,
        63
      ]
    },
    "src/forum/components/NotificationList.js": {
      "expectCount": 10,
      "actualCount": 2,
      "undocumentLines": [
        13,
        33,
        93,
        95,
        97,
        98,
        102,
        107
      ]
    },
    "src/forum/components/NotificationsDropdown.js": {
      "expectCount": 10,
      "actualCount": 0,
      "undocumentLines": [
        5,
        6,
        17,
        26,
        37,
        46,
        54,
        58,
        62,
        66
      ]
    },
    "src/forum/components/NotificationsPage.js": {
      "expectCount": 4,
      "actualCount": 1,
      "undocumentLines": [
        9,
        13,
        16
      ]
    },
    "src/forum/components/Post.js": {
      "expectCount": 12,
      "actualCount": 7,
      "undocumentLines": [
        20,
        22,
        36,
        56,
        61
      ]
    },
    "src/forum/components/PostEdited.js": {
      "expectCount": 4,
      "actualCount": 1,
      "undocumentLines": [
        14,
        18,
        32
      ]
    },
    "src/forum/components/PostMeta.js": {
      "expectCount": 3,
      "actualCount": 2,
      "undocumentLines": [
        15
      ]
    },
    "src/forum/components/PostPreview.js": {
      "expectCount": 2,
      "actualCount": 1,
      "undocumentLines": [
        16
      ]
    },
    "src/forum/components/PostStream.js": {
      "expectCount": 21,
      "actualCount": 10,
      "undocumentLines": [
        1,
        21,
        23,
        24,
        25,
        28,
        111,
        116,
        124,
        158,
        191
      ]
    },
    "src/forum/components/PostStreamScrubber.js": {
      "expectCount": 22,
      "actualCount": 5,
      "undocumentLines": [
        16,
        18,
        19,
        20,
        26,
        97,
        109,
        123,
        124,
        125,
        140,
        171,
        211,
        219,
        228,
        242,
        256
      ]
    },
    "src/forum/components/PostUser.js": {
      "expectCount": 5,
      "actualCount": 3,
      "undocumentLines": [
        17,
        50
      ]
    },
    "src/forum/components/PostsUserPage.js": {
      "expectCount": 12,
      "actualCount": 10,
      "undocumentLines": [
        13,
        46
      ]
    },
    "src/forum/components/RenameDiscussionModal.js": {
      "expectCount": 10,
      "actualCount": 1,
      "undocumentLines": [
        9,
        11,
        12,
        13,
        16,
        20,
        24,
        44,
        46
      ]
    },
    "src/forum/components/ReplyComposer.js": {
      "expectCount": 8,
      "actualCount": 3,
      "undocumentLines": [
        7,
        25,
        32,
        66,
        68
      ]
    },
    "src/forum/components/ReplyPlaceholder.js": {
      "expectCount": 3,
      "actualCount": 1,
      "undocumentLines": [
        18,
        51
      ]
    },
    "src/forum/components/Search.tsx": {
      "expectCount": 22,
      "actualCount": 11,
      "undocumentLines": [
        24,
        47,
        49,
        52,
        56,
        92,
        100,
        109,
        120,
        147,
        151
      ]
    },
    "src/forum/components/SessionDropdown.js": {
      "expectCount": 5,
      "actualCount": 2,
      "undocumentLines": [
        14,
        22,
        28
      ]
    },
    "src/forum/components/SettingsPage.js": {
      "expectCount": 8,
      "actualCount": 5,
      "undocumentLines": [
        16,
        22,
        89
      ]
    },
    "src/forum/components/SignUpModal.js": {
      "expectCount": 17,
      "actualCount": 6,
      "undocumentLines": [
        20,
        45,
        49,
        53,
        61,
        65,
        71,
        117,
        142,
        150,
        152
      ]
    },
    "src/forum/components/TerminalPost.js": {
      "expectCount": 2,
      "actualCount": 1,
      "undocumentLines": [
        14
      ]
    },
    "src/forum/components/UserCard.js": {
      "expectCount": 3,
      "actualCount": 2,
      "undocumentLines": [
        26
      ]
    },
    "src/forum/components/UserPage.js": {
      "expectCount": 10,
      "actualCount": 7,
      "undocumentLines": [
        19,
        28,
        31
      ]
    },
    "src/forum/components/UsersSearchSource.tsx": {
      "expectCount": 4,
      "actualCount": 1,
      "undocumentLines": [
        11,
        13,
        27
      ]
    },
    "src/forum/components/WelcomeHero.js": {
      "expectCount": 5,
      "actualCount": 2,
      "undocumentLines": [
        9,
        11,
        14
      ]
    },
    "src/forum/index.ts": {
      "expectCount": 1,
      "actualCount": 0,
      "undocumentLines": [
        9
      ]
    },
    "src/forum/resolvers/DiscussionPageResolver.ts": {
      "expectCount": 5,
      "actualCount": 5,
      "undocumentLines": []
    },
    "src/forum/routes.js": {
      "expectCount": 1,
      "actualCount": 1,
      "undocumentLines": []
    },
    "src/forum/states/ComposerState.js": {
      "expectCount": 25,
      "actualCount": 21,
      "undocumentLines": [
        6,
        7,
        76,
        77
      ]
    },
    "src/forum/states/DiscussionListState.ts": {
      "expectCount": 14,
      "actualCount": 12,
      "undocumentLines": [
        9,
        57
      ]
    },
    "src/forum/states/GlobalSearchState.ts": {
      "expectCount": 12,
      "actualCount": 11,
      "undocumentLines": [
        10
      ]
    },
    "src/forum/states/NotificationListState.ts": {
      "expectCount": 7,
      "actualCount": 4,
      "undocumentLines": [
        9,
        29,
        30
      ]
    },
    "src/forum/states/PostStreamState.js": {
      "expectCount": 37,
      "actualCount": 23,
      "undocumentLines": [
        4,
        5,
        20,
        21,
        22,
        23,
        50,
        51,
        64,
        107,
        108,
        109,
        112,
        200
      ]
    },
    "src/forum/states/SearchState.ts": {
      "expectCount": 10,
      "actualCount": 8,
      "undocumentLines": [
        8,
        16
      ]
    },
    "src/forum/utils/History.js": {
      "expectCount": 10,
      "actualCount": 9,
      "undocumentLines": [
        15
      ]
    },
    "src/forum/utils/KeyboardNavigatable.ts": {
      "expectCount": 12,
      "actualCount": 11,
      "undocumentLines": [
        12
      ]
    },
    "src/forum/utils/Pane.js": {
      "expectCount": 15,
      "actualCount": 13,
      "undocumentLines": [
        8,
        106
      ]
    },
    "src/forum/utils/alertEmailConfirmation.js": {
      "expectCount": 1,
      "actualCount": 1,
      "undocumentLines": []
    },
    "src/forum/utils/isSafariMobile.ts": {
      "expectCount": 1,
      "actualCount": 1,
      "undocumentLines": []
    },
    "src/forum/utils/slidable.js": {
      "expectCount": 1,
      "actualCount": 1,
      "undocumentLines": []
    }
  }
}