{
  "type": "File",
  "start": 0,
  "end": 475,
  "loc": {
    "start": {
      "line": 1,
      "column": 0
    },
    "end": {
      "line": 22,
      "column": 0
    }
  },
  "program": {
    "type": "Program",
    "start": 0,
    "end": 475,
    "loc": {
      "start": {
        "line": 1,
        "column": 0
      },
      "end": {
        "line": 22,
        "column": 0
      }
    },
    "sourceType": "module",
    "body": [
      {
        "type": "ImportDeclaration",
        "start": 0,
        "end": 47,
        "loc": {
          "start": {
            "line": 1,
            "column": 0
          },
          "end": {
            "line": 1,
            "column": 47
          }
        },
        "specifiers": [
          {
            "type": "ImportDefaultSpecifier",
            "start": 7,
            "end": 16,
            "loc": {
              "start": {
                "line": 1,
                "column": 7
              },
              "end": {
                "line": 1,
                "column": 16
              }
            },
            "local": {
              "type": "Identifier",
              "start": 7,
              "end": 16,
              "loc": {
                "start": {
                  "line": 1,
                  "column": 7
                },
                "end": {
                  "line": 1,
                  "column": 16
                },
                "identifierName": "Component"
              },
              "name": "Component"
            }
          }
        ],
        "source": {
          "type": "StringLiteral",
          "start": 22,
          "end": 46,
          "loc": {
            "start": {
              "line": 1,
              "column": 22
            },
            "end": {
              "line": 1,
              "column": 46
            }
          },
          "extra": {
            "rawValue": "../../common/Component",
            "raw": "'../../common/Component'"
          },
          "value": "../../common/Component"
        }
      },
      {
        "type": "ImportDeclaration",
        "start": 48,
        "end": 99,
        "loc": {
          "start": {
            "line": 2,
            "column": 0
          },
          "end": {
            "line": 2,
            "column": 51
          }
        },
        "specifiers": [
          {
            "type": "ImportDefaultSpecifier",
            "start": 55,
            "end": 63,
            "loc": {
              "start": {
                "line": 2,
                "column": 7
              },
              "end": {
                "line": 2,
                "column": 15
              }
            },
            "local": {
              "type": "Identifier",
              "start": 55,
              "end": 63,
              "loc": {
                "start": {
                  "line": 2,
                  "column": 7
                },
                "end": {
                  "line": 2,
                  "column": 15
                },
                "identifierName": "ItemList"
              },
              "name": "ItemList"
            }
          }
        ],
        "source": {
          "type": "StringLiteral",
          "start": 69,
          "end": 98,
          "loc": {
            "start": {
              "line": 2,
              "column": 21
            },
            "end": {
              "line": 2,
              "column": 50
            }
          },
          "extra": {
            "rawValue": "../../common/utils/ItemList",
            "raw": "'../../common/utils/ItemList'"
          },
          "value": "../../common/utils/ItemList"
        },
        "trailingComments": [
          {
            "type": "CommentBlock",
            "value": "*\n * The `LogInButtons` component displays a collection of social login buttons.\n ",
            "start": 101,
            "end": 187,
            "loc": {
              "start": {
                "line": 4,
                "column": 0
              },
              "end": {
                "line": 6,
                "column": 3
              }
            }
          }
        ]
      },
      {
        "type": "ExportDefaultDeclaration",
        "start": 188,
        "end": 474,
        "loc": {
          "start": {
            "line": 7,
            "column": 0
          },
          "end": {
            "line": 21,
            "column": 1
          }
        },
        "declaration": {
          "type": "ClassDeclaration",
          "start": 203,
          "end": 474,
          "loc": {
            "start": {
              "line": 7,
              "column": 15
            },
            "end": {
              "line": 21,
              "column": 1
            }
          },
          "id": {
            "type": "Identifier",
            "start": 209,
            "end": 221,
            "loc": {
              "start": {
                "line": 7,
                "column": 21
              },
              "end": {
                "line": 7,
                "column": 33
              },
              "identifierName": "LogInButtons"
            },
            "name": "LogInButtons",
            "leadingComments": null
          },
          "superClass": {
            "type": "Identifier",
            "start": 230,
            "end": 239,
            "loc": {
              "start": {
                "line": 7,
                "column": 42
              },
              "end": {
                "line": 7,
                "column": 51
              },
              "identifierName": "Component"
            },
            "name": "Component"
          },
          "body": {
            "type": "ClassBody",
            "start": 240,
            "end": 474,
            "loc": {
              "start": {
                "line": 7,
                "column": 52
              },
              "end": {
                "line": 21,
                "column": 1
              }
            },
            "body": [
              {
                "type": "ClassMethod",
                "start": 244,
                "end": 329,
                "loc": {
                  "start": {
                    "line": 8,
                    "column": 2
                  },
                  "end": {
                    "line": 10,
                    "column": 3
                  }
                },
                "static": false,
                "computed": false,
                "key": {
                  "type": "Identifier",
                  "start": 244,
                  "end": 248,
                  "loc": {
                    "start": {
                      "line": 8,
                      "column": 2
                    },
                    "end": {
                      "line": 8,
                      "column": 6
                    },
                    "identifierName": "view"
                  },
                  "name": "view"
                },
                "kind": "method",
                "id": null,
                "generator": false,
                "expression": false,
                "async": false,
                "params": [],
                "body": {
                  "type": "BlockStatement",
                  "start": 251,
                  "end": 329,
                  "loc": {
                    "start": {
                      "line": 8,
                      "column": 9
                    },
                    "end": {
                      "line": 10,
                      "column": 3
                    }
                  },
                  "body": [
                    {
                      "type": "ReturnStatement",
                      "start": 257,
                      "end": 325,
                      "loc": {
                        "start": {
                          "line": 9,
                          "column": 4
                        },
                        "end": {
                          "line": 9,
                          "column": 72
                        }
                      },
                      "argument": {
                        "type": "JSXElement",
                        "start": 264,
                        "end": 324,
                        "loc": {
                          "start": {
                            "line": 9,
                            "column": 11
                          },
                          "end": {
                            "line": 9,
                            "column": 71
                          }
                        },
                        "openingElement": {
                          "type": "JSXOpeningElement",
                          "start": 264,
                          "end": 294,
                          "loc": {
                            "start": {
                              "line": 9,
                              "column": 11
                            },
                            "end": {
                              "line": 9,
                              "column": 41
                            }
                          },
                          "attributes": [
                            {
                              "type": "JSXAttribute",
                              "start": 269,
                              "end": 293,
                              "loc": {
                                "start": {
                                  "line": 9,
                                  "column": 16
                                },
                                "end": {
                                  "line": 9,
                                  "column": 40
                                }
                              },
                              "name": {
                                "type": "JSXIdentifier",
                                "start": 269,
                                "end": 278,
                                "loc": {
                                  "start": {
                                    "line": 9,
                                    "column": 16
                                  },
                                  "end": {
                                    "line": 9,
                                    "column": 25
                                  }
                                },
                                "name": "className"
                              },
                              "value": {
                                "type": "StringLiteral",
                                "start": 279,
                                "end": 293,
                                "loc": {
                                  "start": {
                                    "line": 9,
                                    "column": 26
                                  },
                                  "end": {
                                    "line": 9,
                                    "column": 40
                                  }
                                },
                                "extra": null,
                                "value": "LogInButtons"
                              }
                            }
                          ],
                          "name": {
                            "type": "JSXIdentifier",
                            "start": 265,
                            "end": 268,
                            "loc": {
                              "start": {
                                "line": 9,
                                "column": 12
                              },
                              "end": {
                                "line": 9,
                                "column": 15
                              }
                            },
                            "name": "div"
                          },
                          "selfClosing": false
                        },
                        "closingElement": {
                          "type": "JSXClosingElement",
                          "start": 318,
                          "end": 324,
                          "loc": {
                            "start": {
                              "line": 9,
                              "column": 65
                            },
                            "end": {
                              "line": 9,
                              "column": 71
                            }
                          },
                          "name": {
                            "type": "JSXIdentifier",
                            "start": 320,
                            "end": 323,
                            "loc": {
                              "start": {
                                "line": 9,
                                "column": 67
                              },
                              "end": {
                                "line": 9,
                                "column": 70
                              }
                            },
                            "name": "div"
                          }
                        },
                        "children": [
                          {
                            "type": "JSXExpressionContainer",
                            "start": 294,
                            "end": 318,
                            "loc": {
                              "start": {
                                "line": 9,
                                "column": 41
                              },
                              "end": {
                                "line": 9,
                                "column": 65
                              }
                            },
                            "expression": {
                              "type": "CallExpression",
                              "start": 295,
                              "end": 317,
                              "loc": {
                                "start": {
                                  "line": 9,
                                  "column": 42
                                },
                                "end": {
                                  "line": 9,
                                  "column": 64
                                }
                              },
                              "callee": {
                                "type": "MemberExpression",
                                "start": 295,
                                "end": 315,
                                "loc": {
                                  "start": {
                                    "line": 9,
                                    "column": 42
                                  },
                                  "end": {
                                    "line": 9,
                                    "column": 62
                                  }
                                },
                                "object": {
                                  "type": "CallExpression",
                                  "start": 295,
                                  "end": 307,
                                  "loc": {
                                    "start": {
                                      "line": 9,
                                      "column": 42
                                    },
                                    "end": {
                                      "line": 9,
                                      "column": 54
                                    }
                                  },
                                  "callee": {
                                    "type": "MemberExpression",
                                    "start": 295,
                                    "end": 305,
                                    "loc": {
                                      "start": {
                                        "line": 9,
                                        "column": 42
                                      },
                                      "end": {
                                        "line": 9,
                                        "column": 52
                                      }
                                    },
                                    "object": {
                                      "type": "ThisExpression",
                                      "start": 295,
                                      "end": 299,
                                      "loc": {
                                        "start": {
                                          "line": 9,
                                          "column": 42
                                        },
                                        "end": {
                                          "line": 9,
                                          "column": 46
                                        }
                                      }
                                    },
                                    "property": {
                                      "type": "Identifier",
                                      "start": 300,
                                      "end": 305,
                                      "loc": {
                                        "start": {
                                          "line": 9,
                                          "column": 47
                                        },
                                        "end": {
                                          "line": 9,
                                          "column": 52
                                        },
                                        "identifierName": "items"
                                      },
                                      "name": "items"
                                    },
                                    "computed": false
                                  },
                                  "arguments": []
                                },
                                "property": {
                                  "type": "Identifier",
                                  "start": 308,
                                  "end": 315,
                                  "loc": {
                                    "start": {
                                      "line": 9,
                                      "column": 55
                                    },
                                    "end": {
                                      "line": 9,
                                      "column": 62
                                    },
                                    "identifierName": "toArray"
                                  },
                                  "name": "toArray"
                                },
                                "computed": false
                              },
                              "arguments": []
                            }
                          }
                        ]
                      }
                    }
                  ],
                  "directives": [],
                  "trailingComments": null
                },
                "trailingComments": [
                  {
                    "type": "CommentBlock",
                    "value": "*\n   * Build a list of LogInButton components.\n   *\n   * @return {ItemList}\n   * @public\n   ",
                    "start": 333,
                    "end": 429,
                    "loc": {
                      "start": {
                        "line": 12,
                        "column": 2
                      },
                      "end": {
                        "line": 17,
                        "column": 5
                      }
                    }
                  }
                ]
              },
              {
                "type": "ClassMethod",
                "start": 432,
                "end": 472,
                "loc": {
                  "start": {
                    "line": 18,
                    "column": 2
                  },
                  "end": {
                    "line": 20,
                    "column": 3
                  }
                },
                "static": false,
                "computed": false,
                "key": {
                  "type": "Identifier",
                  "start": 432,
                  "end": 437,
                  "loc": {
                    "start": {
                      "line": 18,
                      "column": 2
                    },
                    "end": {
                      "line": 18,
                      "column": 7
                    },
                    "identifierName": "items"
                  },
                  "name": "items",
                  "leadingComments": null
                },
                "kind": "method",
                "id": null,
                "generator": false,
                "expression": false,
                "async": false,
                "params": [],
                "body": {
                  "type": "BlockStatement",
                  "start": 440,
                  "end": 472,
                  "loc": {
                    "start": {
                      "line": 18,
                      "column": 10
                    },
                    "end": {
                      "line": 20,
                      "column": 3
                    }
                  },
                  "body": [
                    {
                      "type": "ReturnStatement",
                      "start": 446,
                      "end": 468,
                      "loc": {
                        "start": {
                          "line": 19,
                          "column": 4
                        },
                        "end": {
                          "line": 19,
                          "column": 26
                        }
                      },
                      "argument": {
                        "type": "NewExpression",
                        "start": 453,
                        "end": 467,
                        "loc": {
                          "start": {
                            "line": 19,
                            "column": 11
                          },
                          "end": {
                            "line": 19,
                            "column": 25
                          }
                        },
                        "callee": {
                          "type": "Identifier",
                          "start": 457,
                          "end": 465,
                          "loc": {
                            "start": {
                              "line": 19,
                              "column": 15
                            },
                            "end": {
                              "line": 19,
                              "column": 23
                            },
                            "identifierName": "ItemList"
                          },
                          "name": "ItemList"
                        },
                        "arguments": []
                      }
                    }
                  ],
                  "directives": []
                },
                "leadingComments": [
                  {
                    "type": "CommentBlock",
                    "value": "*\n   * Build a list of LogInButton components.\n   *\n   * @return {ItemList}\n   * @public\n   ",
                    "start": 333,
                    "end": 429,
                    "loc": {
                      "start": {
                        "line": 12,
                        "column": 2
                      },
                      "end": {
                        "line": 17,
                        "column": 5
                      }
                    }
                  }
                ]
              }
            ]
          },
          "leadingComments": [
            {
              "type": "CommentBlock",
              "value": "*\n * The `LogInButtons` component displays a collection of social login buttons.\n ",
              "start": 101,
              "end": 187,
              "loc": {
                "start": {
                  "line": 4,
                  "column": 0
                },
                "end": {
                  "line": 6,
                  "column": 3
                }
              }
            }
          ],
          "trailingComments": []
        },
        "leadingComments": [
          {
            "type": "CommentBlock",
            "value": "*\n * The `LogInButtons` component displays a collection of social login buttons.\n ",
            "start": 101,
            "end": 187,
            "loc": {
              "start": {
                "line": 4,
                "column": 0
              },
              "end": {
                "line": 6,
                "column": 3
              }
            }
          }
        ]
      }
    ],
    "directives": []
  },
  "comments": [
    {
      "type": "CommentBlock",
      "value": "*\n * The `LogInButtons` component displays a collection of social login buttons.\n ",
      "start": 101,
      "end": 187,
      "loc": {
        "start": {
          "line": 4,
          "column": 0
        },
        "end": {
          "line": 6,
          "column": 3
        }
      }
    },
    {
      "type": "CommentBlock",
      "value": "*\n   * Build a list of LogInButton components.\n   *\n   * @return {ItemList}\n   * @public\n   ",
      "start": 333,
      "end": 429,
      "loc": {
        "start": {
          "line": 12,
          "column": 2
        },
        "end": {
          "line": 17,
          "column": 5
        }
      }
    }
  ],
  "tokens": [
    {
      "type": {
        "label": "import",
        "keyword": "import",
        "beforeExpr": false,
        "startsExpr": true,
        "rightAssociative": false,
        "isLoop": false,
        "isAssign": false,
        "prefix": false,
        "postfix": false,
        "binop": null,
        "updateContext": null
      },
      "value": "import",
      "start": 0,
      "end": 6,
      "loc": {
        "start": {
          "line": 1,
          "column": 0
        },
        "end": {
          "line": 1,
          "column": 6
        }
      }
    },
    {
      "type": {
        "label": "name",
        "beforeExpr": false,
        "startsExpr": true,
        "rightAssociative": false,
        "isLoop": false,
        "isAssign": false,
        "prefix": false,
        "postfix": false,
        "binop": null
      },
      "value": "Component",
      "start": 7,
      "end": 16,
      "loc": {
        "start": {
          "line": 1,
          "column": 7
        },
        "end": {
          "line": 1,
          "column": 16
        }
      }
    },
    {
      "type": {
        "label": "name",
        "beforeExpr": false,
        "startsExpr": true,
        "rightAssociative": false,
        "isLoop": false,
        "isAssign": false,
        "prefix": false,
        "postfix": false,
        "binop": null
      },
      "value": "from",
      "start": 17,
      "end": 21,
      "loc": {
        "start": {
          "line": 1,
          "column": 17
        },
        "end": {
          "line": 1,
          "column": 21
        }
      }
    },
    {
      "type": {
        "label": "string",
        "beforeExpr": false,
        "startsExpr": true,
        "rightAssociative": false,
        "isLoop": false,
        "isAssign": false,
        "prefix": false,
        "postfix": false,
        "binop": null,
        "updateContext": null
      },
      "value": "../../common/Component",
      "start": 22,
      "end": 46,
      "loc": {
        "start": {
          "line": 1,
          "column": 22
        },
        "end": {
          "line": 1,
          "column": 46
        }
      }
    },
    {
      "type": {
        "label": ";",
        "beforeExpr": true,
        "startsExpr": false,
        "rightAssociative": false,
        "isLoop": false,
        "isAssign": false,
        "prefix": false,
        "postfix": false,
        "binop": null,
        "updateContext": null
      },
      "start": 46,
      "end": 47,
      "loc": {
        "start": {
          "line": 1,
          "column": 46
        },
        "end": {
          "line": 1,
          "column": 47
        }
      }
    },
    {
      "type": {
        "label": "import",
        "keyword": "import",
        "beforeExpr": false,
        "startsExpr": true,
        "rightAssociative": false,
        "isLoop": false,
        "isAssign": false,
        "prefix": false,
        "postfix": false,
        "binop": null,
        "updateContext": null
      },
      "value": "import",
      "start": 48,
      "end": 54,
      "loc": {
        "start": {
          "line": 2,
          "column": 0
        },
        "end": {
          "line": 2,
          "column": 6
        }
      }
    },
    {
      "type": {
        "label": "name",
        "beforeExpr": false,
        "startsExpr": true,
        "rightAssociative": false,
        "isLoop": false,
        "isAssign": false,
        "prefix": false,
        "postfix": false,
        "binop": null
      },
      "value": "ItemList",
      "start": 55,
      "end": 63,
      "loc": {
        "start": {
          "line": 2,
          "column": 7
        },
        "end": {
          "line": 2,
          "column": 15
        }
      }
    },
    {
      "type": {
        "label": "name",
        "beforeExpr": false,
        "startsExpr": true,
        "rightAssociative": false,
        "isLoop": false,
        "isAssign": false,
        "prefix": false,
        "postfix": false,
        "binop": null
      },
      "value": "from",
      "start": 64,
      "end": 68,
      "loc": {
        "start": {
          "line": 2,
          "column": 16
        },
        "end": {
          "line": 2,
          "column": 20
        }
      }
    },
    {
      "type": {
        "label": "string",
        "beforeExpr": false,
        "startsExpr": true,
        "rightAssociative": false,
        "isLoop": false,
        "isAssign": false,
        "prefix": false,
        "postfix": false,
        "binop": null,
        "updateContext": null
      },
      "value": "../../common/utils/ItemList",
      "start": 69,
      "end": 98,
      "loc": {
        "start": {
          "line": 2,
          "column": 21
        },
        "end": {
          "line": 2,
          "column": 50
        }
      }
    },
    {
      "type": {
        "label": ";",
        "beforeExpr": true,
        "startsExpr": false,
        "rightAssociative": false,
        "isLoop": false,
        "isAssign": false,
        "prefix": false,
        "postfix": false,
        "binop": null,
        "updateContext": null
      },
      "start": 98,
      "end": 99,
      "loc": {
        "start": {
          "line": 2,
          "column": 50
        },
        "end": {
          "line": 2,
          "column": 51
        }
      }
    },
    {
      "type": "CommentBlock",
      "value": "*\n * The `LogInButtons` component displays a collection of social login buttons.\n ",
      "start": 101,
      "end": 187,
      "loc": {
        "start": {
          "line": 4,
          "column": 0
        },
        "end": {
          "line": 6,
          "column": 3
        }
      }
    },
    {
      "type": {
        "label": "export",
        "keyword": "export",
        "beforeExpr": false,
        "startsExpr": false,
        "rightAssociative": false,
        "isLoop": false,
        "isAssign": false,
        "prefix": false,
        "postfix": false,
        "binop": null,
        "updateContext": null
      },
      "value": "export",
      "start": 188,
      "end": 194,
      "loc": {
        "start": {
          "line": 7,
          "column": 0
        },
        "end": {
          "line": 7,
          "column": 6
        }
      }
    },
    {
      "type": {
        "label": "default",
        "keyword": "default",
        "beforeExpr": true,
        "startsExpr": false,
        "rightAssociative": false,
        "isLoop": false,
        "isAssign": false,
        "prefix": false,
        "postfix": false,
        "binop": null,
        "updateContext": null
      },
      "value": "default",
      "start": 195,
      "end": 202,
      "loc": {
        "start": {
          "line": 7,
          "column": 7
        },
        "end": {
          "line": 7,
          "column": 14
        }
      }
    },
    {
      "type": {
        "label": "class",
        "keyword": "class",
        "beforeExpr": false,
        "startsExpr": false,
        "rightAssociative": false,
        "isLoop": false,
        "isAssign": false,
        "prefix": false,
        "postfix": false,
        "binop": null,
        "updateContext": null
      },
      "value": "class",
      "start": 203,
      "end": 208,
      "loc": {
        "start": {
          "line": 7,
          "column": 15
        },
        "end": {
          "line": 7,
          "column": 20
        }
      }
    },
    {
      "type": {
        "label": "name",
        "beforeExpr": false,
        "startsExpr": true,
        "rightAssociative": false,
        "isLoop": false,
        "isAssign": false,
        "prefix": false,
        "postfix": false,
        "binop": null
      },
      "value": "LogInButtons",
      "start": 209,
      "end": 221,
      "loc": {
        "start": {
          "line": 7,
          "column": 21
        },
        "end": {
          "line": 7,
          "column": 33
        }
      }
    },
    {
      "type": {
        "label": "extends",
        "keyword": "extends",
        "beforeExpr": true,
        "startsExpr": false,
        "rightAssociative": false,
        "isLoop": false,
        "isAssign": false,
        "prefix": false,
        "postfix": false,
        "binop": null,
        "updateContext": null
      },
      "value": "extends",
      "start": 222,
      "end": 229,
      "loc": {
        "start": {
          "line": 7,
          "column": 34
        },
        "end": {
          "line": 7,
          "column": 41
        }
      }
    },
    {
      "type": {
        "label": "name",
        "beforeExpr": false,
        "startsExpr": true,
        "rightAssociative": false,
        "isLoop": false,
        "isAssign": false,
        "prefix": false,
        "postfix": false,
        "binop": null
      },
      "value": "Component",
      "start": 230,
      "end": 239,
      "loc": {
        "start": {
          "line": 7,
          "column": 42
        },
        "end": {
          "line": 7,
          "column": 51
        }
      }
    },
    {
      "type": {
        "label": "{",
        "beforeExpr": true,
        "startsExpr": true,
        "rightAssociative": false,
        "isLoop": false,
        "isAssign": false,
        "prefix": false,
        "postfix": false,
        "binop": null
      },
      "start": 240,
      "end": 241,
      "loc": {
        "start": {
          "line": 7,
          "column": 52
        },
        "end": {
          "line": 7,
          "column": 53
        }
      }
    },
    {
      "type": {
        "label": "name",
        "beforeExpr": false,
        "startsExpr": true,
        "rightAssociative": false,
        "isLoop": false,
        "isAssign": false,
        "prefix": false,
        "postfix": false,
        "binop": null
      },
      "value": "view",
      "start": 244,
      "end": 248,
      "loc": {
        "start": {
          "line": 8,
          "column": 2
        },
        "end": {
          "line": 8,
          "column": 6
        }
      }
    },
    {
      "type": {
        "label": "(",
        "beforeExpr": true,
        "startsExpr": true,
        "rightAssociative": false,
        "isLoop": false,
        "isAssign": false,
        "prefix": false,
        "postfix": false,
        "binop": null
      },
      "start": 248,
      "end": 249,
      "loc": {
        "start": {
          "line": 8,
          "column": 6
        },
        "end": {
          "line": 8,
          "column": 7
        }
      }
    },
    {
      "type": {
        "label": ")",
        "beforeExpr": false,
        "startsExpr": false,
        "rightAssociative": false,
        "isLoop": false,
        "isAssign": false,
        "prefix": false,
        "postfix": false,
        "binop": null
      },
      "start": 249,
      "end": 250,
      "loc": {
        "start": {
          "line": 8,
          "column": 7
        },
        "end": {
          "line": 8,
          "column": 8
        }
      }
    },
    {
      "type": {
        "label": "{",
        "beforeExpr": true,
        "startsExpr": true,
        "rightAssociative": false,
        "isLoop": false,
        "isAssign": false,
        "prefix": false,
        "postfix": false,
        "binop": null
      },
      "start": 251,
      "end": 252,
      "loc": {
        "start": {
          "line": 8,
          "column": 9
        },
        "end": {
          "line": 8,
          "column": 10
        }
      }
    },
    {
      "type": {
        "label": "return",
        "keyword": "return",
        "beforeExpr": true,
        "startsExpr": false,
        "rightAssociative": false,
        "isLoop": false,
        "isAssign": false,
        "prefix": false,
        "postfix": false,
        "binop": null,
        "updateContext": null
      },
      "value": "return",
      "start": 257,
      "end": 263,
      "loc": {
        "start": {
          "line": 9,
          "column": 4
        },
        "end": {
          "line": 9,
          "column": 10
        }
      }
    },
    {
      "type": {
        "label": "jsxTagStart",
        "beforeExpr": false,
        "startsExpr": true,
        "rightAssociative": false,
        "isLoop": false,
        "isAssign": false,
        "prefix": false,
        "postfix": false,
        "binop": null
      },
      "start": 264,
      "end": 265,
      "loc": {
        "start": {
          "line": 9,
          "column": 11
        },
        "end": {
          "line": 9,
          "column": 12
        }
      }
    },
    {
      "type": {
        "label": "jsxName",
        "beforeExpr": false,
        "startsExpr": false,
        "rightAssociative": false,
        "isLoop": false,
        "isAssign": false,
        "prefix": false,
        "postfix": false,
        "binop": null,
        "updateContext": null
      },
      "value": "div",
      "start": 265,
      "end": 268,
      "loc": {
        "start": {
          "line": 9,
          "column": 12
        },
        "end": {
          "line": 9,
          "column": 15
        }
      }
    },
    {
      "type": {
        "label": "jsxName",
        "beforeExpr": false,
        "startsExpr": false,
        "rightAssociative": false,
        "isLoop": false,
        "isAssign": false,
        "prefix": false,
        "postfix": false,
        "binop": null,
        "updateContext": null
      },
      "value": "className",
      "start": 269,
      "end": 278,
      "loc": {
        "start": {
          "line": 9,
          "column": 16
        },
        "end": {
          "line": 9,
          "column": 25
        }
      }
    },
    {
      "type": {
        "label": "=",
        "beforeExpr": true,
        "startsExpr": false,
        "rightAssociative": false,
        "isLoop": false,
        "isAssign": true,
        "prefix": false,
        "postfix": false,
        "binop": null,
        "updateContext": null
      },
      "value": "=",
      "start": 278,
      "end": 279,
      "loc": {
        "start": {
          "line": 9,
          "column": 25
        },
        "end": {
          "line": 9,
          "column": 26
        }
      }
    },
    {
      "type": {
        "label": "string",
        "beforeExpr": false,
        "startsExpr": true,
        "rightAssociative": false,
        "isLoop": false,
        "isAssign": false,
        "prefix": false,
        "postfix": false,
        "binop": null,
        "updateContext": null
      },
      "value": "LogInButtons",
      "start": 279,
      "end": 293,
      "loc": {
        "start": {
          "line": 9,
          "column": 26
        },
        "end": {
          "line": 9,
          "column": 40
        }
      }
    },
    {
      "type": {
        "label": "jsxTagEnd",
        "beforeExpr": false,
        "startsExpr": false,
        "rightAssociative": false,
        "isLoop": false,
        "isAssign": false,
        "prefix": false,
        "postfix": false,
        "binop": null
      },
      "start": 293,
      "end": 294,
      "loc": {
        "start": {
          "line": 9,
          "column": 40
        },
        "end": {
          "line": 9,
          "column": 41
        }
      }
    },
    {
      "type": {
        "label": "{",
        "beforeExpr": true,
        "startsExpr": true,
        "rightAssociative": false,
        "isLoop": false,
        "isAssign": false,
        "prefix": false,
        "postfix": false,
        "binop": null
      },
      "start": 294,
      "end": 295,
      "loc": {
        "start": {
          "line": 9,
          "column": 41
        },
        "end": {
          "line": 9,
          "column": 42
        }
      }
    },
    {
      "type": {
        "label": "this",
        "keyword": "this",
        "beforeExpr": false,
        "startsExpr": true,
        "rightAssociative": false,
        "isLoop": false,
        "isAssign": false,
        "prefix": false,
        "postfix": false,
        "binop": null,
        "updateContext": null
      },
      "value": "this",
      "start": 295,
      "end": 299,
      "loc": {
        "start": {
          "line": 9,
          "column": 42
        },
        "end": {
          "line": 9,
          "column": 46
        }
      }
    },
    {
      "type": {
        "label": ".",
        "beforeExpr": false,
        "startsExpr": false,
        "rightAssociative": false,
        "isLoop": false,
        "isAssign": false,
        "prefix": false,
        "postfix": false,
        "binop": null,
        "updateContext": null
      },
      "start": 299,
      "end": 300,
      "loc": {
        "start": {
          "line": 9,
          "column": 46
        },
        "end": {
          "line": 9,
          "column": 47
        }
      }
    },
    {
      "type": {
        "label": "name",
        "beforeExpr": false,
        "startsExpr": true,
        "rightAssociative": false,
        "isLoop": false,
        "isAssign": false,
        "prefix": false,
        "postfix": false,
        "binop": null
      },
      "value": "items",
      "start": 300,
      "end": 305,
      "loc": {
        "start": {
          "line": 9,
          "column": 47
        },
        "end": {
          "line": 9,
          "column": 52
        }
      }
    },
    {
      "type": {
        "label": "(",
        "beforeExpr": true,
        "startsExpr": true,
        "rightAssociative": false,
        "isLoop": false,
        "isAssign": false,
        "prefix": false,
        "postfix": false,
        "binop": null
      },
      "start": 305,
      "end": 306,
      "loc": {
        "start": {
          "line": 9,
          "column": 52
        },
        "end": {
          "line": 9,
          "column": 53
        }
      }
    },
    {
      "type": {
        "label": ")",
        "beforeExpr": false,
        "startsExpr": false,
        "rightAssociative": false,
        "isLoop": false,
        "isAssign": false,
        "prefix": false,
        "postfix": false,
        "binop": null
      },
      "start": 306,
      "end": 307,
      "loc": {
        "start": {
          "line": 9,
          "column": 53
        },
        "end": {
          "line": 9,
          "column": 54
        }
      }
    },
    {
      "type": {
        "label": ".",
        "beforeExpr": false,
        "startsExpr": false,
        "rightAssociative": false,
        "isLoop": false,
        "isAssign": false,
        "prefix": false,
        "postfix": false,
        "binop": null,
        "updateContext": null
      },
      "start": 307,
      "end": 308,
      "loc": {
        "start": {
          "line": 9,
          "column": 54
        },
        "end": {
          "line": 9,
          "column": 55
        }
      }
    },
    {
      "type": {
        "label": "name",
        "beforeExpr": false,
        "startsExpr": true,
        "rightAssociative": false,
        "isLoop": false,
        "isAssign": false,
        "prefix": false,
        "postfix": false,
        "binop": null
      },
      "value": "toArray",
      "start": 308,
      "end": 315,
      "loc": {
        "start": {
          "line": 9,
          "column": 55
        },
        "end": {
          "line": 9,
          "column": 62
        }
      }
    },
    {
      "type": {
        "label": "(",
        "beforeExpr": true,
        "startsExpr": true,
        "rightAssociative": false,
        "isLoop": false,
        "isAssign": false,
        "prefix": false,
        "postfix": false,
        "binop": null
      },
      "start": 315,
      "end": 316,
      "loc": {
        "start": {
          "line": 9,
          "column": 62
        },
        "end": {
          "line": 9,
          "column": 63
        }
      }
    },
    {
      "type": {
        "label": ")",
        "beforeExpr": false,
        "startsExpr": false,
        "rightAssociative": false,
        "isLoop": false,
        "isAssign": false,
        "prefix": false,
        "postfix": false,
        "binop": null
      },
      "start": 316,
      "end": 317,
      "loc": {
        "start": {
          "line": 9,
          "column": 63
        },
        "end": {
          "line": 9,
          "column": 64
        }
      }
    },
    {
      "type": {
        "label": "}",
        "beforeExpr": false,
        "startsExpr": false,
        "rightAssociative": false,
        "isLoop": false,
        "isAssign": false,
        "prefix": false,
        "postfix": false,
        "binop": null
      },
      "start": 317,
      "end": 318,
      "loc": {
        "start": {
          "line": 9,
          "column": 64
        },
        "end": {
          "line": 9,
          "column": 65
        }
      }
    },
    {
      "type": {
        "label": "jsxTagStart",
        "beforeExpr": false,
        "startsExpr": true,
        "rightAssociative": false,
        "isLoop": false,
        "isAssign": false,
        "prefix": false,
        "postfix": false,
        "binop": null
      },
      "start": 318,
      "end": 319,
      "loc": {
        "start": {
          "line": 9,
          "column": 65
        },
        "end": {
          "line": 9,
          "column": 66
        }
      }
    },
    {
      "type": {
        "label": "/",
        "beforeExpr": true,
        "startsExpr": false,
        "rightAssociative": false,
        "isLoop": false,
        "isAssign": false,
        "prefix": false,
        "postfix": false,
        "binop": 10,
        "updateContext": null
      },
      "value": "/",
      "start": 319,
      "end": 320,
      "loc": {
        "start": {
          "line": 9,
          "column": 66
        },
        "end": {
          "line": 9,
          "column": 67
        }
      }
    },
    {
      "type": {
        "label": "jsxName",
        "beforeExpr": false,
        "startsExpr": false,
        "rightAssociative": false,
        "isLoop": false,
        "isAssign": false,
        "prefix": false,
        "postfix": false,
        "binop": null,
        "updateContext": null
      },
      "value": "div",
      "start": 320,
      "end": 323,
      "loc": {
        "start": {
          "line": 9,
          "column": 67
        },
        "end": {
          "line": 9,
          "column": 70
        }
      }
    },
    {
      "type": {
        "label": "jsxTagEnd",
        "beforeExpr": false,
        "startsExpr": false,
        "rightAssociative": false,
        "isLoop": false,
        "isAssign": false,
        "prefix": false,
        "postfix": false,
        "binop": null
      },
      "start": 323,
      "end": 324,
      "loc": {
        "start": {
          "line": 9,
          "column": 70
        },
        "end": {
          "line": 9,
          "column": 71
        }
      }
    },
    {
      "type": {
        "label": ";",
        "beforeExpr": true,
        "startsExpr": false,
        "rightAssociative": false,
        "isLoop": false,
        "isAssign": false,
        "prefix": false,
        "postfix": false,
        "binop": null,
        "updateContext": null
      },
      "start": 324,
      "end": 325,
      "loc": {
        "start": {
          "line": 9,
          "column": 71
        },
        "end": {
          "line": 9,
          "column": 72
        }
      }
    },
    {
      "type": {
        "label": "}",
        "beforeExpr": false,
        "startsExpr": false,
        "rightAssociative": false,
        "isLoop": false,
        "isAssign": false,
        "prefix": false,
        "postfix": false,
        "binop": null
      },
      "start": 328,
      "end": 329,
      "loc": {
        "start": {
          "line": 10,
          "column": 2
        },
        "end": {
          "line": 10,
          "column": 3
        }
      }
    },
    {
      "type": "CommentBlock",
      "value": "*\n   * Build a list of LogInButton components.\n   *\n   * @return {ItemList}\n   * @public\n   ",
      "start": 333,
      "end": 429,
      "loc": {
        "start": {
          "line": 12,
          "column": 2
        },
        "end": {
          "line": 17,
          "column": 5
        }
      }
    },
    {
      "type": {
        "label": "name",
        "beforeExpr": false,
        "startsExpr": true,
        "rightAssociative": false,
        "isLoop": false,
        "isAssign": false,
        "prefix": false,
        "postfix": false,
        "binop": null
      },
      "value": "items",
      "start": 432,
      "end": 437,
      "loc": {
        "start": {
          "line": 18,
          "column": 2
        },
        "end": {
          "line": 18,
          "column": 7
        }
      }
    },
    {
      "type": {
        "label": "(",
        "beforeExpr": true,
        "startsExpr": true,
        "rightAssociative": false,
        "isLoop": false,
        "isAssign": false,
        "prefix": false,
        "postfix": false,
        "binop": null
      },
      "start": 437,
      "end": 438,
      "loc": {
        "start": {
          "line": 18,
          "column": 7
        },
        "end": {
          "line": 18,
          "column": 8
        }
      }
    },
    {
      "type": {
        "label": ")",
        "beforeExpr": false,
        "startsExpr": false,
        "rightAssociative": false,
        "isLoop": false,
        "isAssign": false,
        "prefix": false,
        "postfix": false,
        "binop": null
      },
      "start": 438,
      "end": 439,
      "loc": {
        "start": {
          "line": 18,
          "column": 8
        },
        "end": {
          "line": 18,
          "column": 9
        }
      }
    },
    {
      "type": {
        "label": "{",
        "beforeExpr": true,
        "startsExpr": true,
        "rightAssociative": false,
        "isLoop": false,
        "isAssign": false,
        "prefix": false,
        "postfix": false,
        "binop": null
      },
      "start": 440,
      "end": 441,
      "loc": {
        "start": {
          "line": 18,
          "column": 10
        },
        "end": {
          "line": 18,
          "column": 11
        }
      }
    },
    {
      "type": {
        "label": "return",
        "keyword": "return",
        "beforeExpr": true,
        "startsExpr": false,
        "rightAssociative": false,
        "isLoop": false,
        "isAssign": false,
        "prefix": false,
        "postfix": false,
        "binop": null,
        "updateContext": null
      },
      "value": "return",
      "start": 446,
      "end": 452,
      "loc": {
        "start": {
          "line": 19,
          "column": 4
        },
        "end": {
          "line": 19,
          "column": 10
        }
      }
    },
    {
      "type": {
        "label": "new",
        "keyword": "new",
        "beforeExpr": true,
        "startsExpr": true,
        "rightAssociative": false,
        "isLoop": false,
        "isAssign": false,
        "prefix": false,
        "postfix": false,
        "binop": null,
        "updateContext": null
      },
      "value": "new",
      "start": 453,
      "end": 456,
      "loc": {
        "start": {
          "line": 19,
          "column": 11
        },
        "end": {
          "line": 19,
          "column": 14
        }
      }
    },
    {
      "type": {
        "label": "name",
        "beforeExpr": false,
        "startsExpr": true,
        "rightAssociative": false,
        "isLoop": false,
        "isAssign": false,
        "prefix": false,
        "postfix": false,
        "binop": null
      },
      "value": "ItemList",
      "start": 457,
      "end": 465,
      "loc": {
        "start": {
          "line": 19,
          "column": 15
        },
        "end": {
          "line": 19,
          "column": 23
        }
      }
    },
    {
      "type": {
        "label": "(",
        "beforeExpr": true,
        "startsExpr": true,
        "rightAssociative": false,
        "isLoop": false,
        "isAssign": false,
        "prefix": false,
        "postfix": false,
        "binop": null
      },
      "start": 465,
      "end": 466,
      "loc": {
        "start": {
          "line": 19,
          "column": 23
        },
        "end": {
          "line": 19,
          "column": 24
        }
      }
    },
    {
      "type": {
        "label": ")",
        "beforeExpr": false,
        "startsExpr": false,
        "rightAssociative": false,
        "isLoop": false,
        "isAssign": false,
        "prefix": false,
        "postfix": false,
        "binop": null
      },
      "start": 466,
      "end": 467,
      "loc": {
        "start": {
          "line": 19,
          "column": 24
        },
        "end": {
          "line": 19,
          "column": 25
        }
      }
    },
    {
      "type": {
        "label": ";",
        "beforeExpr": true,
        "startsExpr": false,
        "rightAssociative": false,
        "isLoop": false,
        "isAssign": false,
        "prefix": false,
        "postfix": false,
        "binop": null,
        "updateContext": null
      },
      "start": 467,
      "end": 468,
      "loc": {
        "start": {
          "line": 19,
          "column": 25
        },
        "end": {
          "line": 19,
          "column": 26
        }
      }
    },
    {
      "type": {
        "label": "}",
        "beforeExpr": false,
        "startsExpr": false,
        "rightAssociative": false,
        "isLoop": false,
        "isAssign": false,
        "prefix": false,
        "postfix": false,
        "binop": null
      },
      "start": 471,
      "end": 472,
      "loc": {
        "start": {
          "line": 20,
          "column": 2
        },
        "end": {
          "line": 20,
          "column": 3
        }
      }
    },
    {
      "type": {
        "label": "}",
        "beforeExpr": false,
        "startsExpr": false,
        "rightAssociative": false,
        "isLoop": false,
        "isAssign": false,
        "prefix": false,
        "postfix": false,
        "binop": null
      },
      "start": 473,
      "end": 474,
      "loc": {
        "start": {
          "line": 21,
          "column": 0
        },
        "end": {
          "line": 21,
          "column": 1
        }
      }
    },
    {
      "type": {
        "label": "eof",
        "beforeExpr": false,
        "startsExpr": false,
        "rightAssociative": false,
        "isLoop": false,
        "isAssign": false,
        "prefix": false,
        "postfix": false,
        "binop": null,
        "updateContext": null
      },
      "start": 475,
      "end": 475,
      "loc": {
        "start": {
          "line": 22,
          "column": 0
        },
        "end": {
          "line": 22,
          "column": 0
        }
      }
    }
  ]
}